tests/overcli-monitor-test.py
tests/__init__.py
tests/ui-test.py
tests/api_test.py
overc-1.0.9_1.dist-info/metadata.json
overc-1.0.9_1.dist-info/entry_points.txt
overc-1.0.9_1.dist-info/RECORD
overc-1.0.9_1.dist-info/top_level.txt
overc-1.0.9_1.dist-info/DESCRIPTION.rst
overc-1.0.9_1.dist-info/WHEEL
overc-1.0.9_1.dist-info/METADATA
overc/__init__.py
overc/wsgi.py
overc/src/__init__.py
overc/src/init.py
overc/src/bps/__init__.py
overc/src/bps/ui/__init__.py
overc/src/bps/ui/templates/pages/index.htm
overc/src/bps/ui/static/style.css
overc/src/bps/ui/static/config.rb
overc/src/bps/ui/static/main.css
overc/src/bps/ui/static/all.js
overc/src/bps/ui/static/img/favicon-32.png
overc/src/bps/ui/static/img/favicon-128.png
overc/src/bps/ui/static/img/favicon-256.png
overc/src/bps/ui/static/img/favicon-16.png
overc/src/bps/ui/static/img/favicon-24.png
overc/src/bps/ui/static/img/favicon-48.png
overc/src/bps/ui/static/img/favicon.ico
overc/src/bps/ui/static/img/favicon-64.png
overc/src/bps/ui/static/img/icons/state-s2be7a17aa6.png
overc/src/bps/ui/static/img/icons/ajax-loader.gif
overc/src/bps/ui/static/img/icons/state/-blue.png
overc/src/bps/ui/static/img/icons/state/FAIL.png
overc/src/bps/ui/static/img/icons/state/OK.png
overc/src/bps/ui/static/img/icons/state/WARN.png
overc/src/bps/ui/static/img/icons/state/-yellow.png
overc/src/bps/ui/static/img/icons/state/UNK.png
overc/src/bps/ui/static/sass/main.scss
overc/src/bps/ui/static/sass/partials/_base.scss
overc/src/bps/ui/static/sass/partials/_sprites.scss
overc/src/bps/ui/static/sass/lib/_mixins.scss
overc/src/bps/ui/static/.sass-cache/4a0ef57fbc3f3cbf07958219bab54a6fdb6ae05b/_sprite-img.scssc
overc/src/bps/ui/static/.sass-cache/4a0ef57fbc3f3cbf07958219bab54a6fdb6ae05b/_base.scssc
overc/src/bps/ui/static/.sass-cache/ede792fbf8780b94212f443ea8228a0269a4d76e/_inline-block-list.scssc
overc/src/bps/ui/static/.sass-cache/ede792fbf8780b94212f443ea8228a0269a4d76e/_horizontal-list.scssc
overc/src/bps/ui/static/.sass-cache/ede792fbf8780b94212f443ea8228a0269a4d76e/_inline-list.scssc
overc/src/bps/ui/static/.sass-cache/ede792fbf8780b94212f443ea8228a0269a4d76e/_bullets.scssc
