Metadata-Version: 2.0
Name: overc
Version: 1.0.9-1
Summary: Simplistic monitoring solution that is a pleasure to use 
Home-page: https://github.com/kolypto/py-overc
Author: Mark Vartanyan
Author-email: kolypto@gmail.com
License: BSD
Keywords: monitoring
Platform: any
Classifier: Development Status :: 5 - Production/Stable
Classifier: Environment :: Web Environment
Classifier: Framework :: Flask
Classifier: Intended Audience :: Developers
Classifier: Intended Audience :: System Administrators
Classifier: Natural Language :: English
Classifier: Operating System :: OS Independent
Classifier: Programming Language :: Python :: 2
Provides-Extra: _dev
Requires-Dist: wheel; extra == '_dev'
Requires-Dist: nose; extra == '_dev'
Requires-Dist: freezegun; extra == '_dev'
Provides-Extra: server
Requires-Dist: flask (>=0.10.1); extra == 'server'
Requires-Dist: sqlalchemy (>=0.9.6); extra == 'server'
Requires-Dist: mysql-python (>=1.2.5); extra == 'server'
